versionrunner/__init__.py
versionrunner/check_libraries_version.py
versionrunner-0.0.3.dist-info/METADATA
versionrunner-0.0.3.dist-info/WHEEL
versionrunner-0.0.3.dist-info/top_level.txt
versionrunner-0.0.3.dist-info/RECORD
