Metadata-Version: 2.1
Name: versionrunner
Version: 0.0.3
Summary: A library that easily generates a requirements.txt file
Home-page: https://github.com/TCK2001/versionrunner
Author: TCK
Author-email: ekatmdrkd7227@gmail.com
License: MIT
Keywords: version,autoversion,requirements,versionrunner
Requires-Python: >=3
